[
    "How can I use the `takeoffer` command to accept an offer in Verus using the command line?",
    "You can use the `takeoffer` command to accept an offer in Verus using the command line by running a command in the following format:\n\n```\nverus takeoffer fromaddress '{\"txid\":\"txid\" | \"tx\":\"hextx\", \"deliver\":\"fullidnameoriaddresstodeliver\" | {\"currency\":\"currencynameorid\",\"amount\":...}, \"accept\":{\"address\":\"addressorid\",\"currency\":\"currencynameorid\",\"amount\"} | {identitydefinition}}' (returntx) (feeamount)\n```\n\nReplace the placeholders with the actual values for your transaction.",
    "Examples:\n> verus takeoffer fromaddress '{\"txid\":\"txid\" | \"tx\":\"hextx\", \"deliver\":\"fullidnameoriaddresstodeliver\" | {\"currency\":\"currencynameorid\",\"amount\":...}, \"accept\":{\"address\":\"addressorid\",\"currency\":\"currencynameorid\",\"amount\"} | {identitydefinition}}' (returntx) (feeamount)\n> curl --user myusername --data-binary '{\"jsonrpc\": \"1.0\", \"id\":\"curltest\", \"method\": \"takeoffer\", \"params\": [fromaddress {\"txid\":\"txid\" | \"tx\":\"hextx\", \"deliver\":\"fullidnameoriaddresstodeliver\" | {\"currency\":\"currencynameorid\",\"amount\":...}, \"accept\":{\"address\":\"addressorid\",\"currency\":\"currencynameorid\",\"amount\"} | {identitydefinition}} (returntx) (feeamount)] }' -H 'content-type: text/plain;' http://127.0.0.1:27486/",
    "./raw_text_input_api_text/takeoffer"
]