[
    "What is the \"weights\" property used for in a Verus currency definition?",
    "The \"weights\" property is a number array that specifies the relative currency weights. This property is only returned for a liquidity basket and is used to define the relative importance of each currency in the basket.",
    "he currency ID, same as the ID behind the currency\n \"currencyidhex\" : \"hex\",        (string) hex representation of currency ID, getcurrency API supports \"hex:currencyidhex\"\n \"parent\" : \"i-address\",        (string) parent blockchain ID\n \"systemid\" : \"i-address\",       (string) system on which this currency is considered to run\n \"launchsystemid\" : \"i-address\",    (string) system from which this currency was launched\n \"notarizationprotocol\" : n       (int) protocol number that determines variations in cross-chain or bridged notarizations\n \"proofprotocol\" : n          (int) protocol number that determines variations in cross-chain or bridged proofs\n \"startblock\" : n,           (int) block # on this chain, which must be notarized into block one of the chain\n \"endblock\" : n,            (int) block # after which, this chain's useful life is considered to be over\n \"currencies\" : \"[\"i-address\", ...]\",  (stringarray) currencies that can be converted to this currency at launch or makeup a liquidity basket\n \"weights\" : \"[n, ...]\",        (numberarray) relative currency weights (only returned for a liquidity basket)\n \"conversions\" : \"[n, ...]\",      (numberarray) pre-launch conversion rates for non-fractional currencies\n \"minpreconversion\" : \"[n, ...]\",    (numberarray) minimum amounts required in pre-conversions for currency to launch\n \"currencies\" : \"[\"i-address\", ...]\",  (stringarray) currencies that can be converted to this currency at launch or makeup a liquidity basket\n \"currencynames\" : \"{\"i-address\":\"fullname\",...}\", (obj) i-addresses mapped to fully qualified names of all sub-currencies\n \"initialsupply\" : n,          (number) initial currency supply for fractional currencies before preallocation or issuance\n \"prelaunchcarveout\" : n,        (number) pre-launc",
    "./raw_text_input_wiki/clifaq-02_verus_commands.md"
]