[
    "What are the required and optional arguments for the `getidentitieswithrecovery` command?",
    "The required argument is `identityid`, which is a string representing the ID or i-address of the recovery authority. The optional arguments are `fromheight`, `toheight`, and `unspent`. `fromheight` and `toheight` are numbers that specify the block height range to search for identities, and `unspent` is a boolean that filters the results to only include active ID UTXOs as of the current block height.",
    "#### Arguments:\n```json\n{\n  \"identityid\":\"idori-address\" (string, required) returns all identities where this ID or i-address is the recovery authority\n  \"fromheight\":n        (number, optional, default=0) Search for qualified identities modified from this height forward only\n  \"toheight\":n         (number, optional, default=0) Search for qualified identities only up until this height (0 == no limit)\n  \"unspent\":bool        (bool, optional, default=false) if true, this will only return active ID UTXOs as of the current block height\n}\n```\n#### Result:\n```json\n[                 (array) array of matching identities\n {identityobject},        (object) identity with additional member \"txout\" with txhash and output index\n ...\n]\n```\n####Examples:\n```bash\n> verus getidentitieswithrecovery '{\"identityid\":\"idori-address\",\"fromheight\":height,\"toheight\":height,\"unspent\":false}'\n> curl --user myusername --data-binary '{\"jsonrpc\": \"1.0\", \"id\":\"curltest\", \"method\": \"getidentitieswithrecovery\", \"params\": ['{\"identityid\":\"idori-address\",\"fromheight\":height,\"toheight\":height,\"unspent\":false}'] }' -H 'content-type: text/plain;' http://127.0.0.1:27486/\n```\n### `getidentitieswithrevocation '{\"identityid\":\"idori-address\", \"fromheight\":height, \"toheight\":height, \"unspent\":false}'`#### Arguments:\n```json\n{\n  \"identityid\":\"idori-address\" (string, required) returns all identities where this ID or i-address is the revocation authority\n  \"fromheight\":n        (number, optional, default=0) Search for qualified identities modified from this height forward only\n  \"toheight\":n         (number, optional, default=0) Search for qualified identities only up until this height (0 == no limit)\n  \"unspent\":bool        (bool, optional, default=false) if true, this will only return active ID UTXOs as of the current block hei",
    "./raw_text_input_wiki/clifaq-02_verus_commands.md"
]