[
    [
        [
            "What is the correct syntax to use the `getvdxfid` method using the Verus CLI?",
            "The `getvdxfid` method is not used with the Verus CLI, but rather as a JSON RPC request. The correct syntax for this request is:\n```\ncurl --user myusername --data-binary '{\"jsonrpc\": \"1.0\", \"id\":\"curltest\", \"method\": \"getvdxfid\", \"params\": [\"idname::userdefinedgroup.subgroup.publishedname\"] }' -H 'content-type: text/plain;' http://127.0.0.1:27486/\n```\nThis will send a JSON RPC request to the Verus JSON RPC server.",
            "As json rpc\n> curl --user myusername --data-binary '{\"jsonrpc\": \"1.0\", \"id\":\"curltest\", \"method\": \"getvdxfid\", \"params\": [\"idname::userdefinedgroup.subgroup.publishedname\"] }' -H 'content-type: text/plain;' http://127.0.0.1:27486/",
            "./raw_text_input_api_text/getvdxfid"
        ],
        [
            "Is it possible to use the `getvdxfid` method without specifying a username and password?",
            "No, it is not possible to use the `getvdxfid` method without specifying a username and password. The `--user` option is required to authenticate the request with the Verus JSON RPC server.",
            "As json rpc\n> curl --user myusername --data-binary '{\"jsonrpc\": \"1.0\", \"id\":\"curltest\", \"method\": \"getvdxfid\", \"params\": [\"idname::userdefinedgroup.subgroup.publishedname\"] }' -H 'content-type: text/plain;' http://127.0.0.1:27486/",
            "./raw_text_input_api_text/getvdxfid"
        ]
    ],
    "will",
    "be",
    "replaced",
    "f80b6924-e6c9-479b-8303-2a135abe045f"
]